streamlit_signin_auth_ui/__init__.py
streamlit_signin_auth_ui/utils.py
streamlit_signin_auth_ui/widgets.py
streamlit_signin_auth_ui-1.3.3.dist-info/LICENSE.txt
streamlit_signin_auth_ui-1.3.3.dist-info/METADATA
streamlit_signin_auth_ui-1.3.3.dist-info/WHEEL
streamlit_signin_auth_ui-1.3.3.dist-info/top_level.txt
streamlit_signin_auth_ui-1.3.3.dist-info/RECORD
