Metadata-Version: 2.1
Name: streamlit_signin_auth_ui
Version: 1.3.3
Summary: Login/Sign-up page with Streamlit,the user's data are stored in a Google Sheets file as database,also the lables of widgets are in Frensh language.
Author-email: TAOUFIQ ABDESSAMAD <samadtaoufik@gmail.com>
Project-URL: Homepage, https://github.com/GitSamad88/streamlit-signin-ui
Project-URL: Issues, https://github.com/GitSamad88/streamlit-signin-ui/issues
Classifier: Programming Language :: Python :: 3
Classifier: License :: OSI Approved :: MIT License
Classifier: Operating System :: OS Independent
Requires-Python: >=3.10
License-File: LICENSE.txt
Requires-Dist: requests >=2.31.0
Requires-Dist: streamlit >=1.31.0
Requires-Dist: gspread >=5.12.4
Requires-Dist: pandas >=2.2.0
Requires-Dist: oauth2client >=4.1.3
Requires-Dist: google-api-python-client >=2.119.0
Requires-Dist: argon2-cffi
Requires-Dist: streamlit-lottie
Requires-Dist: streamlit-option-menu
Requires-Dist: streamlit-cookies-manager-hotpatched ==0.2.1
